{"share":{"title":"FC Chelsea - News zum Verein","url":"https://www.transfermarkt.de/fc-chelsea/news/verein/631","description":"Verlängerungen, Transfers, Spielberichte & Co.: Alle relevanten und aktuellen News vom Verein FC Chelsea auf einen Blick."},"news":[{"id":"444512","newsHeadline":"Höchste Abwehr-Ausgaben: Bayern zahlte 145 Millionen mehr als Real – England-Trio oben","timestamp":1728127800,"newsSecondImage":"https://tmssl.akamaized.net//images/wappen/homepageSmall/281.png?lm=1467356331","newsDate":"05.10.2024","fullNewsDate":"Samstag, 5. Oktober 2024","newsTime":"13:30","newsSource":"Transfermarkt","newsStartPageFlag":null,"newsShortMessageFlag":null,"newsTeaser":"Seit 2000","newsFirstImage":"https://tmssl.akamaized.net//images/wappen/normal/27.png?lm=1498251238","newsSpotlightFirstImage":"","newsSpotlightSecondImage":"","newsCategoryID":"32","newsCategoryTag":"Statistiken","newsTickerFlag":"0","newsUpdateFlag":"0","newsAdFlag":"0","spotlightPriority":""},{"id":"444635","newsHeadline":"Maresca: Chelsea ist „nicht bereit“, um mit Man City oder Arsenal mithalten zu können","timestamp":1728051600,"newsSecondImage":"https://tmssl.akamaized.net//images/wappen/homepageSmall/631.png?lm=1682435911","newsDate":"04.10.2024","fullNewsDate":"Freitag, 4. Oktober 2024","newsTime":"16:20","newsSource":"BBC/Transfermarkt","newsStartPageFlag":null,"newsShortMessageFlag":null,"newsTeaser":"Formstärkstes englisches Team ","newsFirstImage":"https://img.a.transfermarkt.technology/portrait/medium/53749-1717428745.jpg?lm=1","newsSpotlightFirstImage":"","newsSpotlightSecondImage":"","newsCategoryID":"0","newsCategoryTag":"News","newsTickerFlag":"0","newsUpdateFlag":"0","newsAdFlag":"0","spotlightPriority":""},{"id":"444481","newsHeadline":"Bester Spieler der Premier League? Marktwert-Gewinner Palmer bei Chelsea Mann der Stunde","timestamp":1727798400,"newsSecondImage":"https://tmssl.akamaized.net//images/wappen/homepageSmall/631.png?lm=1682435911","newsDate":"01.10.2024","fullNewsDate":"Dienstag, 1. Oktober 2024","newsTime":"18:00","newsSource":"Transfermarkt.co.uk","newsStartPageFlag":null,"newsShortMessageFlag":null,"newsTeaser":"Ligaweit meiste Scorer seit 2023","newsFirstImage":"https://img.a.transfermarkt.technology/portrait/medium/568177-1712320986.jpg?lm=1","newsSpotlightFirstImage":"","newsSpotlightSecondImage":"","newsCategoryID":"0","newsCategoryTag":"News","newsTickerFlag":"0","newsUpdateFlag":"0","newsAdFlag":"0","spotlightPriority":""},{"id":"444364","newsHeadline":"Marktwert-Rekord: Haaland überholt Real-Trio um Mbappé – Minus für de Ligt & Gündoğan","timestamp":1727780400,"newsSecondImage":"https://tmssl.akamaized.net//images/logo/homepageSmall/gb1.png?lm=1521104656","newsDate":"01.10.2024","fullNewsDate":"Dienstag, 1. Oktober 2024","newsTime":"13:00","newsSource":"Transfermarkt.co.uk","newsStartPageFlag":null,"newsShortMessageFlag":null,"newsTeaser":"Premier-League-Update","newsFirstImage":"https://img.a.transfermarkt.technology/portrait/medium/418560-1709108116.png?lm=1","newsSpotlightFirstImage":"","newsSpotlightSecondImage":"","newsCategoryID":"14","newsCategoryTag":"Marktwerte-Update","newsTickerFlag":"0","newsUpdateFlag":"0","newsAdFlag":"0","spotlightPriority":""},{"id":"444374","newsHeadline":"Meiste Ausgaben für Torhüter: Chelsea baut Vorsprung mit Jørgensen & Penders aus","timestamp":1727607300,"newsSecondImage":"https://tmssl.akamaized.net//images/wappen/homepageSmall/631.png?lm=1682435911","newsDate":"29.09.2024","fullNewsDate":"Sonntag, 29. September 2024","newsTime":"12:55","newsSource":"Transfermarkt","newsStartPageFlag":null,"newsShortMessageFlag":null,"newsTeaser":"Bundesliga-Investitionen gering","newsFirstImage":"https://img.a.transfermarkt.technology/portrait/medium/585323-1718280485.jpg?lm=1","newsSpotlightFirstImage":"","newsSpotlightSecondImage":"","newsCategoryID":"32","newsCategoryTag":"Statistiken","newsTickerFlag":"0","newsUpdateFlag":"0","newsAdFlag":"0","spotlightPriority":""},{"id":"444401","newsHeadline":"Chelseas Palmer erzielt frühesten Viererpack – Hürzelers erste Niederlage in England","timestamp":1727549631,"newsSecondImage":"https://tmssl.akamaized.net//images/logo/homepageSmall/gb1.png?lm=1521104656","newsDate":"28.09.2024","fullNewsDate":"Samstag, 28. September 2024","newsTime":"20:53","newsSource":"Transfermarkt","newsStartPageFlag":null,"newsShortMessageFlag":null,"newsTeaser":"Premier-League-Novum","newsFirstImage":"https://img.a.transfermarkt.technology/portrait/medium/568177-1712320986.jpg?lm=1","newsSpotlightFirstImage":"","newsSpotlightSecondImage":"","newsCategoryID":"32","newsCategoryTag":"Statistiken","newsTickerFlag":"0","newsUpdateFlag":"0","newsAdFlag":"0","spotlightPriority":""},{"id":"444393","newsHeadline":"Musiala: In England gelernt, „mit Freiheit zu spielen“ – Mit 7 Colwill in den Schatten gestellt","timestamp":1727522843,"newsSecondImage":"https://tmssl.akamaized.net//images/wappen/homepageSmall/180.png?lm=1444560086","newsDate":"28.09.2024","fullNewsDate":"Samstag, 28. September 2024","newsTime":"13:27","newsSource":"Guardian/AZ","newsStartPageFlag":null,"newsShortMessageFlag":null,"newsTeaser":"Bayern-Profi über Anfänge","newsFirstImage":"https://img.a.transfermarkt.technology/portrait/medium/580195-1711745441.jpg?lm=1","newsSpotlightFirstImage":"","newsSpotlightSecondImage":"","newsCategoryID":"0","newsCategoryTag":"News","newsTickerFlag":"0","newsUpdateFlag":"0","newsAdFlag":"0","spotlightPriority":""},{"id":"444133","newsHeadline":"Liverpool schiebt sich an Tabellenspitze – Achillessehne stoppt Füllkrug bei West Ham","timestamp":1726936740,"newsSecondImage":"https://tmssl.akamaized.net//images/logo/homepageSmall/gb1.png?lm=1521104656","newsDate":"21.09.2024","fullNewsDate":"Samstag, 21. September 2024","newsTime":"18:39","newsSource":"dpa/TM","newsStartPageFlag":null,"newsShortMessageFlag":null,"newsTeaser":"Díaz-Doppelpack","newsFirstImage":"https://img.a.transfermarkt.technology/portrait/medium/480692-1697903145.jpg?lm=1","newsSpotlightFirstImage":"","newsSpotlightSecondImage":"","newsCategoryID":"0","newsCategoryTag":"News","newsTickerFlag":"0","newsUpdateFlag":"0","newsAdFlag":"0","spotlightPriority":""},{"id":"444011","newsHeadline":"Teuerste Kader: Chelsea zahlte mehr als Bayern, BVB und Leverkusen zusammen","timestamp":1726668976,"newsSecondImage":"","newsDate":"18.09.2024","fullNewsDate":"Mittwoch, 18. September 2024","newsTime":"16:16","newsSource":"Transfermarkt","newsStartPageFlag":null,"newsShortMessageFlag":null,"newsTeaser":"Neuer Führender bei Wertschöpfung","newsFirstImage":"https://tmssl.akamaized.net//images/wappen/normal/631.png?lm=1682435911","newsSpotlightFirstImage":"","newsSpotlightSecondImage":"","newsCategoryID":"32","newsCategoryTag":"Statistiken","newsTickerFlag":"0","newsUpdateFlag":"0","newsAdFlag":"0","spotlightPriority":""},{"id":"443855","newsHeadline":"Chelsea gibt Fofana an Süper-Lig-Aufsteiger Göztepe ab – Wertvollster Spieler im Kader","timestamp":1726301520,"newsSecondImage":"https://tmssl.akamaized.net//images/wappen/homepageSmall/1467.png?lm=1441199242","newsDate":"14.09.2024","fullNewsDate":"Samstag, 14. September 2024","newsTime":"10:12","newsSource":"Göztepe","newsStartPageFlag":null,"newsShortMessageFlag":null,"newsTeaser":"Mit Klausel wie bei Union","newsFirstImage":"https://img.a.transfermarkt.technology/portrait/medium/787232-1691614259.jpg?lm=1","newsSpotlightFirstImage":"","newsSpotlightSecondImage":"","newsCategoryID":"135","newsCategoryTag":"Transfers & Gerüchte","newsTickerFlag":"1","newsUpdateFlag":"0","newsAdFlag":"0","spotlightPriority":""}]}